docs/source/conf.py
expyre/__init__.py
expyre/config.py
expyre/func.py
expyre/jobsdb.py
expyre/resources.py
expyre/subprocess.py
expyre/system.py
expyre/units.py
expyre/util.py
expyre/cli/__init__.py
expyre/cli/cli.py
expyre/schedulers/__init__.py
expyre/schedulers/base.py
expyre/schedulers/local.py
expyre/schedulers/pbs.py
expyre/schedulers/sge.py
expyre/schedulers/slurm.py
expyre_wfl-0.1.6.dist-info/LICENSE
expyre_wfl-0.1.6.dist-info/METADATA
expyre_wfl-0.1.6.dist-info/WHEEL
expyre_wfl-0.1.6.dist-info/entry_points.txt
expyre_wfl-0.1.6.dist-info/top_level.txt
expyre_wfl-0.1.6.dist-info/RECORD
