Metadata-Version: 2.2
Name: expyre-wfl
Version: 0.1.6
License:                     GNU GENERAL PUBLIC LICENSE
Requires-Python: >=3.9
License-File: LICENSE
Requires-Dist: click>=7.0
